{
  "title": "Radware Live Threat Map Top Attacked Regions",
  "source": "https://livethreatmap.radware.com/",
  "generatedAt": "2026-07-19T16:15:32+00:00",
  "intervals": {
    "hour": [
      {
        "name": "US",
        "value": 8
      },
      {
        "name": "CA",
        "value": 5
      },
      {
        "name": "IT",
        "value": 4
      },
      {
        "name": "AE",
        "value": 4
      },
      {
        "name": "HK",
        "value": 3
      }
    ],
    "day": [
      {
        "name": "US",
        "value": 8
      },
      {
        "name": "SG",
        "value": 5
      },
      {
        "name": "HK",
        "value": 4
      },
      {
        "name": "CA",
        "value": 4
      },
      {
        "name": "IN",
        "value": 3
      }
    ]
  }
}
