{
  "title": "Radware Live Threat Map Top Attacked Regions",
  "source": "https://livethreatmap.radware.com/",
  "generatedAt": "2026-07-17T21:09:23+00:00",
  "intervals": {
    "hour": [
      {
        "name": "US",
        "value": 9
      },
      {
        "name": "IN",
        "value": 4
      },
      {
        "name": "CA",
        "value": 4
      },
      {
        "name": "HK",
        "value": 3
      },
      {
        "name": "AU",
        "value": 3
      }
    ],
    "day": [
      {
        "name": "US",
        "value": 9
      },
      {
        "name": "SG",
        "value": 4
      },
      {
        "name": "IN",
        "value": 4
      },
      {
        "name": "CA",
        "value": 3
      },
      {
        "name": "AU",
        "value": 3
      }
    ]
  }
}
